analyzerportfolio/__init__.py
analyzerportfolio/ai.py
analyzerportfolio/bmg.py
analyzerportfolio/config.py
analyzerportfolio/graphics.py
analyzerportfolio/logger.py
analyzerportfolio/metrics.py
analyzerportfolio/optimization.py
analyzerportfolio/utils.py
analyzerportfolio-0.2.4.dist-info/licenses/LICENSE
analyzerportfolio-0.2.4.dist-info/METADATA
analyzerportfolio-0.2.4.dist-info/WHEEL
analyzerportfolio-0.2.4.dist-info/top_level.txt
analyzerportfolio-0.2.4.dist-info/RECORD
