Metadata-Version: 2.4
Name: analyzerportfolio
Version: 0.2.4
Summary: A Python package for stock portfolio analysis and optimization.
Home-page: https://github.com/washednico/analyzerportfolio
Author: Nicola Fochi, Leonardo Mario di Gennaro
Author-email: portfolioanalyzer-devs@proton.me
License: MIT
Classifier: Programming Language :: Python :: 3
Classifier: Operating System :: OS Independent
Classifier: License :: OSI Approved :: MIT License
Requires-Python: >=3.6
License-File: LICENSE
Requires-Dist: openai>=1.43.0
Requires-Dist: pandas>=1.5.1
Requires-Dist: yfinance>=0.2.54
Requires-Dist: numpy>=1.26.4
Requires-Dist: plotly>=5.18.0
Requires-Dist: arch>=7.0.0
Requires-Dist: scipy>=1.14.0
Requires-Dist: statsmodels>=0.14.1
Requires-Dist: nbformat>=4.2.0
Requires-Dist: xbbg>=0.1.0
Dynamic: author
Dynamic: author-email
Dynamic: classifier
Dynamic: description
Dynamic: description-content-type
Dynamic: home-page
Dynamic: license
Dynamic: license-file
Dynamic: requires-dist
Dynamic: requires-python
Dynamic: summary
